pydantic_vcon/__init__.py
pydantic_vcon/models.py
pydantic_vcon-0.0.2.dist-info/LICENSE
pydantic_vcon-0.0.2.dist-info/METADATA
pydantic_vcon-0.0.2.dist-info/WHEEL
pydantic_vcon-0.0.2.dist-info/RECORD
