Metadata-Version: 2.3
Name: pydantic-vcon
Version: 0.0.2
Summary: A Pydantic-based implementation of the vCon (Virtual Conversation Container) format
License: MIT
Author: Thomas Howe
Author-email: ghostofbasho@gmail.com
Requires-Python: >=3.8
Classifier: License :: OSI Approved :: MIT License
Classifier: Programming Language :: Python :: 3
Classifier: Programming Language :: Python :: 3.8
Classifier: Programming Language :: Python :: 3.9
Classifier: Programming Language :: Python :: 3.10
Classifier: Programming Language :: Python :: 3.11
Classifier: Programming Language :: Python :: 3.12
Classifier: Programming Language :: Python :: 3.13
Requires-Dist: pydantic (>=2.0.0)
Project-URL: Homepage, https://github.com/howethomas/pydantic-vcon
Project-URL: Repository, https://github.com/howethomas/pydantic-vcon
